<?xml version='1.0' encoding='UTF-8'?>
<xml>
  <body>
    <div>
      <p><persName>GUILHELMUS</persName>Minatensis. Siehe: DURANTI: Rationale divino¬  rum officiorum  GUILLAUME D’ AUVERGNE. Siche: <persName>GUILLERMUS</persName>Episcopus  Parisiensis  <persName>GUILLERMUS</persName>Episcopus Parisiensis <placeName>Strassburg</placeName>, <persName>J. Knobloch</persName><date>1507</date> GVILHERMVS EPISCOPVS(Parisiensis De collationibus  et pluralitate ecclesiasti- corum benefi! ciorum.! <persName>Albertus</persName> magnus De adherendo soli deo. Sanctus Bonauentura ad  fratres men dicantes, quales esse debeant erga pre- latos &amp; amp; ecclesiarum rectores.  Am Schluss: Prodierunt hec foeliciter ad dei lau! dem  ex officina <persName>Ioannis Knoblouchi</persName>. An! no salutis nostre. M. D.  VIl. kalend. Iulias.  40, Antiq., 42 unn. Bll., Sign. A- H, Kopft., Init.  Auf der Rücks, des Titelbl.: <persName>IoANNI RYNCo</persName>vrbis Agrippine  ciui consulari... Iaco.! Vuimphelingius sese commendat.... — Ex Argen. iij. kal. Iunias <date>1507</date>. &amp; quot;R101717. Prov.: Trübner, <placeName>Strassburg</placeName>10. VI. <date>1887</date>; 5M.  2. ER.* R 101369. Prov.: Geschenk der Stadt Heilbronn.  Stadtbibl. <placeName>Strassburg</placeName>581; Proctor II Sectio I Nr. 10.053: Lon¬  don Brit. Museum; Schmidt VII Nr. 30( mit Trennungsstrich: men  dicantes):« Jadis Bibl. de Strasbourg, Incun. No 52, Bibl. St. Guil¬  laume, Strasbourg»; Walter: Schlettstadt Nr. 1453. GK( mit Tren¬  nungsstrich hinter mendicantes): SB <placeName>Berlin</placeName>, UB <placeName>Breslau</placeName>.  1058  <persName>GUINTERIUS Johannes Andernacus</persName><placeName>Strassburg</placeName>,[ <persName>J. Knobloch</persName>Rihel?] 1547  INSTRVCTI- ON TRES VTILE, PAR] LAQVELLE VN CHACVN  SE POVR-] ra maintenir en santé, tant au temps! de peste,  comme en autre temps, par! Maistre <persName idref="034363610">Jehan Guinter</persName>d’ An¬  717  </p>
    </div>
  </body>
</xml>
