<?xml version='1.0' encoding='UTF-8'?>
<xml>
  <body>
    <div>
      <p><persName>KALILA u. Caspar</persName>DIMNA. Siche: BUCH DER WEISHEIT  KANTZ  <placeName>Strassburg</placeName>, <persName>M. Flach</persName><date>1524</date> Von der Euangeli schen Messz. Mit schönen Ge¬  betten, vor vnd nach der entphahung des Sacraments.  Am Schluss: Impressum per Martinum anno xxiiij. ( Rücks. leer.)  80, Got., 8 unn. Bll., Sign. A, Init., Titeleinfassung( HEB  Tafel X Nr. 6).  R100.587. Prov.: Bibl. Ch. Schmidt mit Exlibris, darunter » <placeName>Berlin</placeName><date>1871</date>.  Neudruck in: Beiträge zur Reformationsgeschichte von <placeName>Strassburg</placeName> von G. Heinrich Simon.[ Mitteilungen aus dem Antiquariate von S.  Calvary e Co., I. Jahrg. 2. Heft.] <placeName>Berlin</placeName><date>1868</date>.  Schmidt VI Nr. 75.  Bibliographie Kantz siche: Schottenloher I Nr. 9587- 9591. 1302  <persName idref="027723720">KARLSTADT Andreas Bodenstein</persName>von  <placeName>Strassburg</placeName>[ Joh. Prüss] <date>1524</date> Von Engelen vnd Teüf- felen ein Sermon.  Botenstein von Carolstadt.( Rücks, leer.)  Am Schluss: Getruckt zâ Straszburg! <persName>M. Flach</persName>D. xxiiij.  40, Got., 10 unn. Bll., Sign. a- e, Marg., Init. V. &amp; quot;R100.588. Prov.: <persName>M. Flach</persName>Breslauer, <placeName>Berlin</placeName>24. VIII. <date>1916</date>, 11 <persName>M. Flach</persName> </p>
    </div>
  </body>
</xml>
