<?xml version='1.0' encoding='UTF-8'?>
<xml>
  <body>
    <div>
      <p><placeName>Strassburg</placeName>und zwar Joh. Grüninger. Siehe: Proctor II  Sectio I Nr. 9887.)  40, Antiq., 18 unn. Bll., Sign. a- c, Init. F. V.  Auf der Rücks. des Titelbl.: Querela. la, vuympfelingij de  Fra- tre Thoma Murner.  Bl. a 2a: <persName>Petrus Guntherus Jacobi</persName>Murena lectori praecipue  Argentinensibus salutem...  Defensio Germanide  Mympfelingũ quam frater Thomas  Murner lmpugnauit.  Epistola, <persName>C. Molfu</persName>Juniors  D. D.ad F. Tho. Murner in defensu¬  onem lacobi Vympfelingi. ~  Melim ( ZENVS)  Pr Nos eenMer re  SHO  QCECN  B  OH ( Zu Nr. 1064)  </p>
    </div>
  </body>
</xml>
