<?xml version='1.0' encoding='UTF-8'?>
<xml>
  <body>
    <div>
      <p><persName>, Jacobus</persName>: Ars conficiendi epistulas.—( Strasbourg <persName>, Jacobus</persName> <persName>Georges Husner</persName><date>s. d.</date><date>s.</date>) <persName>, Jacobus</persName>in-4°.  Voulliéme: <placeName>Berlin</placeName>2534.  592  RAETSELBUCH: Wölchem an kurzweill thet zerrinden...—  Strasbourg <date>s. d.</date><date>s.</date><persName>, Jacobus</persName>in-4°.  Hain 13676.  593  <persName>RAMPEGOLUS Antonius de</persName><persName>, Jacobus</persName>: Compendium Bibliae seu Aureum  Bibliae Repertorium.—( Strasbourg <persName>, Jacobus</persName>impr. des Vitas  Copinger II <persName>, Jacobus</persName>5025 <persName>, Jacobus</persName>Polain 3298 <persName>, Jacobus</persName>Proctor 434.  594  RAYMUNDUS Gurcensis: Resolution betr. den Ablass des  goldenen Jahres( en bas allemand):( Hlyr volget nae  eyn seker Resolutzye...—( Strasbourg <persName>, Jacobus</persName><persName idref="140812156">Jean Prüss</persName>(?)  <date>1500</date>) <persName>, Jacobus</persName>placard in- fol.  Borchling- Claussen <persName>, Jacobus</persName>Niederdeutsche Bibliographie n° 328;  Einblattdrucke 1091.  595  REGIMEN: Regimen sanitatis Salernitanum.— Strasbourg <persName>, Jacobus</persName> <persName idref="119108860">Mathias Hupfuff</persName><persName>Mathias Brant</persName>1499 <persName>, Jacobus</persName>in-4°.  Hain 13763; Schmidt V <persName>, Jacobus</persName>n° 9.  596  REGIMEN( Idem)( lat. et allemand).—( Strasbourg <persName>, Jacobus</persName> <persName idref="119108860">Mathias Hupfuff</persName><persName>Mathias Brant</persName><date>1500</date>) <persName>, Jacobus</persName>in-4°.  Copinger II <persName>, Jacobus</persName>5046( auparavant 4978): Schmidt IV <persName>, Jacobus</persName>p. 12 <persName>, Jacobus</persName> n° 1; Schreiber 5062; Voulliéme: <placeName>Berlin</placeName>2563,10; Weller 168. — Musée germanique <placeName>Nuremberg</placeName>.  597  REGIMEN sanitatis... Das ist das Regiment der gesuntheit  durch alle monat des gantzen iors wie man sich halten  soll mit essen und trincken...—( Strasbourg <persName>, Jacobus</persName><persName idref="119108860">Mathias Hupfuff</persName><persName>Mathias Brant</persName> )( <date>vers</date><date>1500</date>) <persName>, Jacobus</persName>in-4°.  Voulliéme: <placeName>Berlin</placeName>2563,11.  598  90  </p>
    </div>
  </body>
</xml>
