<?xml version='1.0' encoding='UTF-8'?>
<xml>
  <body>
    <div>
      <p><persName>.</persName>d’ attente S.  In-40, car <persName>.</persName>goth <persName>.</persName>, 15 ff <persName>.</persName>non ch.— 1 f. blanc, sign <persName>.</persName>A- C, titre courant, &amp; quot;R. 102.238 <persName>.</persName>Prov <persName>.</persName>: J. Halle, Munich, 29/ x, 1935; 35 <date>M. D.</date>De nombreuses  notes mss <persName>.</persName>à la marge des ff <persName>.</persName>et au verso du dernier f.  Manque chez Schmidt <persName>.</persName> 2517  ZENOBIUS  <placeName>Haguenau</placeName>, P. <persName>Brubach</persName><placeName>Brubach</placeName>, 1535  A la suite du texte grec: Zenobij Compendium ueterum  pro! uerbiorum ex Tarraeo et Didy mo collectum, opus lu  culentum&amp; amp; utile <persName>.</persName> <placeName>Haganoae</placeName>Anno <persName>.</persName>XXXV <persName>.</persName>Au- dessous, feuille de lierre ( Verso blanc <persName>.</persName>)  A la fin: èv t̃ αyαvóς oπò Hlérgoυ Bpobbaxyé! ou étt...  XAtogO πevrixootocoTλαxoσῶ̀ TEμRO͂.  Au verso, marque typ <persName>.</persName>de <persName>Brubach</persName><placeName>Brubach</placeName>( H.&amp; amp; B. Planche LXIX,  No 4 <persName>.</persName> In-8°, car, grecs, 149 pp. ch <persName>.</persName>, 1 f. non ch <persName>.</persName>, réclames, belles init <persName>.</persName>à fig <persName>.</persName>O,  A et init <persName>.</persName>d’ attente <persName>.</persName> fol <persName>.</persName>2a:... Ioanni!! <persName>Magenpuchio</persName>medici-[] nae doctori Vin-[] centius  Obsopœus <persName>.</persName>S. D...— Ex Onoltzpachio mense Decembri.!Anno <persName>.</persName><date>M. D.</date> XXXV( Préface de 4 pp.) <persName>.</persName> R. 101.563 <persName>.</persName>Prov <persName>.</persName>: Don de la BU <placeName>Kœnigsberg</placeName>, <date>1871</date><persName>.</persName>Notes mss <persName>.</persName> Oxford, Bibl <persName>.</persName>Bodleiana <persName>.</persName>Brunet Vs, <date>1533</date>; édition assez rare: 6 fr <persName>.</persName> 2518  ZEYTUNG  <placeName>Strasbourg</placeName>, Th <persName>.</persName>Berger, <date>1568</date> Warhafftige vnnd erschrockenliche newe Zeytung, von  dem grossen vnd gewaltigen zulauff des Wasserflusz, der  statt Dieterich Bern im welschlandt, vnnd von dem! grossen  schaden, so es nicht allein an denen orten, son- dern auch zu  Vincentz, Padoa, Triendt, vnd im gantzen!! Thal daselbst  gethon <persName>.</persName>Auch von der grossen anzal der!! Stetten, Leut, vnnd  menge der Heuser, so durch dasselb! vmb kommen, verderbt  vnd hinweg gefürt! worden, gantz erbermenlich zuhören <persName>.</persName> Gesche- hen den 30 <persName>.</persName>vnd 31 <persName>.</persName>tag Octobris,( des 1567 <persName>.</persName>Jars <persName>.</persName> Grav <persName>.</persName>sur bois: Dieu apparaît à Noé après le déluge dans un  nuage, de l’ autre côté l’ arc-en-ciel, Noé et ses fils à genoux,  à côté l’ arche <persName>.</persName><date>M. D.</date>LXVIII <persName>.</persName>( Verso blanc <persName>.</persName>)  A la fin: Getruckt zu <placeName>Strasburg</placeName>bey <persName idref="148950043">Thiebolt</persName>Berger am!  Weynmarck zum Treubel <persName>.</persName>Anno <date>1568</date>( Verso blanc <persName>.</persName>)  In-4°, car <persName>.</persName>goth <persName>.</persName>, 4 ff <persName>.</persName>non ch <persName>.</persName>sign <persName>.</persName>A, init <persName>.</persName>goth <persName>.</persName>J.  R. 100.422 <persName>.</persName>Prov <persName>.</persName>: Oscar Rauthe, Berlin, 3/ V, 1915; 30 <date>M. D.</date> 2519  </p>
    </div>
  </body>
</xml>
