<?xml version='1.0' encoding='UTF-8'?>
<xml>
  <body>
    <div>
      <p><persName idref="262208849">Nicolaus Conrad</persName>( Leorinus, Sile¬  Rieger, Joh.( anc. poss.), 924.  sius, 1584), 930, 1052, 1342, 1999-  Rieger, Urbanus( Philiranus), 961,  965, 978.  2008, 2176.  Reuss Edouard( anc. poss.), 43, 198,  Rietsch, Andreas( impr. <placeName>Strasbourg</placeName>),  262, 3, 354, 356, 363, 404, 405, 407-  821.  414, 763, 924, 1288, 1322, 4, 1327-  Riff( Ryff), Walter( Apollinarius Quin¬  29, 1453, 1507, 8, 1665, 1804, 1933,  tus), 30, 1, 587, 1405, 2030- 2046.  1942, 7, 1953, 2057, 2079, 2120,  Rigelius, JJoh.( Meiningensis), 452.  2270, 2298, 9, 2300, 1, 3, 6, 8, 9,  Rihel, Josias( impr. <placeName>Strasbourg</placeName>), 75,  79- 80, 218- 220, 316, 399, 422, 480, 4,  2316, 2407, 2525, 6.  515- 36, 538, 9, 566, 7, 587, 8, 602,  Reuss, F. A., 1168.  Reuss, Joh.( anno 1566), 2340.  610, 659, 661, 2, 6, 805, 819- 21,  Reuss, Sempronius, 1659.  1018- 22, 1059- 61, 1075- 77, 1142,  Reuter, Gottfried( anc. poss. 1626),  1146- 49, 1150, 1183, 4, 1200, 1333,  865.  1373, 4, 1401, 1464, 5, 1473, 1484,  Reynhart( Graf zu Hanau, Canonieus,  1580, 1, 1640, 1879, 1886, 2044- 46,  Argent.), 1048.  2093- 97, 2136, 9, 2140- 43, 2190,  Rhegius, Ernestus, 2009.  2211- 14, 2216- 23, 2233, 2236- 42,  Rhegius, Urbanus, 1014, 2010- 13.  2261, 2, 2327, 2506.  Rhemnius Fannius,( Palaemonis),  Rihel, Théodose( impr. <placeName>Strasbourg</placeName>),  474.  81, 161, 197, 260, 392, 585, 615, 6,  Rhenanus, Beatus, 54, 55, 57, 59, 60,  622, 7, 680- 83, 1031, 1040, 1, 1063,  136, 163, 560, 605, 705, 733, 955,  1113- 18, 1124, 1185, 6, 1199, 1259,  959, 964, 980, 996, 997, 1037, 1050,  1279- 84, 1353, 4, 1375- 81, 1558- 60,  1562, 1641, 1772, 1774, 1939, 1940,  1496, 1584, 1603, 1739, 1868,  1874, 1890, 1892, 2047, 2154, 2369.  1558- 60, 1562, 1641, 1672, 4,  Rhododendrius, Tho.( Pictor), 2486  1938- 40, 2084- 87, 2129, 2132- 35,  Rhomannus, Gallus( Teccensis, Tran¬  2144- 52. 2171, 2, 2198, 2297, 8.  2304, 5, 2315, 2507.  sylvanus), 1083.  Rhosellus, Lucius, 401.  Rihel, Wendelin( impr. <placeName>Strasbourg</placeName>),  Ribadeneira, Petrus, 2190.  74- 77, 87, 8, 91, 101, 2, 211,  Ricardus, Anglicus( medicus, 1581),  213- 217, 247- 249, 303, 371, 2, 6, 8,  9, 382, 3, 9, 404- 411, 413, 444, 8,  2014.  486, 503- 513, 561, 3, 4, 5, 617- 621,  Ricardus( Norwicensis Episcopus An¬  631, 696, 836, 868, 1015- 17, 1030,  glicus), 1750.  1141, 1193, 1222, 1291, 1321, 1337,  Riccius, <persName>Bartholomaeus</persName>( Lugiensis.  1399, 1415, 1451, 1477, 1577- 79,  1535), 2015.  1804, 1904, 6, 1918, 1932, 2057,  Riccius, Vitus( Noricus, anc. poss.  2073, 2091, 2123, 2129- 39, 2209,  1563), 1219.  2271, 2282, 2292, 2312, 3, 2323,  Richardus, Joh.( <placeName>Argentoratensis</placeName>,  2390, 2499, 2504, 5, 2526.  alias Winkel), 1558- 1560.  Rihel, Wendelin( Diaconus ecclesiae  Richart, Paulus( Hagenoensis, 1525),  2371.  <placeName>Argentinae</placeName>), 1663.  Rihel frères( impr. <placeName>Strasbourg</placeName>), 78,  Richolt, Gerg.( anc. poss. 1555), 2041.  Richter, Epp., 2165.  514, 2092, 2210.  Rihel, héritiers, 78.  Richter, H.( <placeName>Strasbourg</placeName>, don 1908)  Rimicius, 98.  1602.  Ringlin, Jacob, 1736.  Richter, Julius( Berlin, anc. poss.  Ringmann( Philesius, 121, 464, 543,  1871), 2132.  635- 37, 668, 9, 830, 947, 8, 950,  Rickel. Voir: Dionysius von Rickel.  1882, 3, 2367, 2406, 2471, 8, 9,  Riedel( Pasteur à Lubeck, don 1877),  2480, 4, 7, 2493, 2527.  1477.  Rioem, Wolf. And.( anc. poss.), 778.  Riedesel, Adolf <persName>Hermann</persName>( Eysenbach,  Risenberger( Liegnitz, Schlesien, anc.  Erbmarschallk zu Hessen), 151,  poss.), 1116, 1281.  1122.  Ritelius(?) Joh.( anc. poss.), 1899.  Riedrer, Fridericus( von Mülhusen in  Hegow), 2016- 18.  Ritter, Fr.: Cat. BM <placeName>Strasbourg</placeName>1776,  7, 1964, 6, 7, 1974, 7, 1985, 8, 1996,  Riegel( avocat Fribourg, anc. poss.  2005, 2008, 2013, 7, 2021, 7, 9.  1871), 536.  2042, 3, 8, 2053, 2060, 2070, 7.  Rieger( Amoenitates Friburg.), 2472,  2090, 3, 2115, 2125, 9, 2143, 6, 8,  2481, 2493, 2496.  </p>
    </div>
  </body>
</xml>
