<?xml version='1.0' encoding='UTF-8'?>
<xml>
  <body>
    <div>
      <p><placeName>Leipzig</placeName>, <date>1871</date>. Au titre  autographe de Zwingli: Sadiano suo.  Bibliographie de Zwingli: Schottenloher II, Nos 23046- 23475.  2532  ZYRL Christian  Strasbourg, Th. Berger, 1572  Rebecca. Ein schöne Hochzeit Co-media, Von der  vermählung des lie- ben Isaacs vnnd Rebeccae, aus dem  vier vnd zwentzigsten Capitel, des Ersten buchs! Mosi,  Sehr lustig vnd lieblich zu! lesen vnnd zu hören.  Zu Weissenburg am Rhein, newgmacht, vnd gespielt  worden.  Ich bin ein Spiegel der gesellen,  Die zu dem Ehstandt greiffen wöllen.  Deszgleichen dieselben Jungkfrawen,  Sollen sich auch hierinn beschawen.  Getruckt zu <placeName>Straszburg</placeName>bey Thie- bolt Berger zum Trübel  am!) Weinmarck, 1573.( Verso blanc.)  A la fin: Getruckt zu <placeName>Straszburg</placeName>! bey Thiebolt Berger,  zum Treü-bel am Weinmarck.( Verso blanc.)  In-8°, car. goth., 40 ff. non ch., dernier f. blanc, réclames, titre rouge  et noir.  fol. A 2a- A 3a: Dem Ehrnuesten Für- 1 sichtigen Ersamen vnd weisen  Vel- 11 ten Helffanten, des Heiligen Römischen!! Reichs Stattvogt, zu  Weissenburg am Rheim, sei- nem Günstigen Junckern, Entbeut  <persName>Christianus</persName>!! Zierle Teutscher Schulmeister daselbst I! sein gutwillige  vnd gehorsame! dienst zuuor... Ge-!l ben zu Weissenburg am Rhein!!  den zwelfften Junij, im!! jar, 1571( Bande d’ ornement).  Au verso de fol. A 3: Die Personen dises Spiels.  fol. A 4a- A 5a: Prologus. Au- dessous: le hérault, la gravure est répétée  fol. E 5b, au-dessus: Beschlusz.  R. 100.409. Prov.: A. Cohn, <placeName>Berlin</placeName>, 4/ V, <date>1885</date>; 90 M. Au bas du titre: « I. W. <date>1798</date>».  Bibliographie de Zyrl: Schottenloher II, Nos 23478- 23478a.  2533  </p>
    </div>
  </body>
</xml>
