<?xml version='1.0' encoding='UTF-8'?>
<xml>
  <body>
    <div>
      <p><persName>Wolfgang Köpfel</persName> <date>(</date><date>1538</date>), in-8°. <date>(</date>Encadrement et marque typ. de  Köpfell.  <date>(</date>B N Strasbourg, R 102.604 <date>(</date>2) Ritter, Rép, n° 1948). 3035  PSALTER: mit aller Kirchenübung die man bey der Christ¬  lichen Gemein zu <placeName>Straszburg</placeName>und anders pflägt zu singen... — Strasbourg, <persName>Wolfgang Köpfel</persName><date>(</date>1539), in-120. <date>(</date>Encadre¬  ment et marque typ. de Köpfell.  Hubert, n° 30: Bibl. S. Guillaume, Strasbourg; Wackernagel,  p. 155.  3036  PSALTER: Der gantze Psalter Davids... Gesangsweise gefasset  durch M. Cyriacum Spangenberg...— Gedruckt zu  <placeName>Frankfurt</placeName>a. M. 1582 bei Christoff Raben in Verlegung  Bernhard Jobins, Buchhändler in Strassburg, in-80.  Vogeleis p. 347.  3037  PSALTERIUM correctum et hymni.— <date>(</date>Strasbourg, <date>Jean Prüss</date><persName idref="140812156">Jean Prüss</persName><persName>Jean Knobloch</persName> 1502), in-120.  Panzer 11, 356; Schmidt III, n° 35; Vogeleis, p. 163. 3038  PSALTERIUM: Cantica et hymni. Cum carmine <persName>Johannis</persName> Gallinarii.— <date>(</date>Strasbourg, <date>Jean Prüss</date><persName idref="140812156">Jean Prüss</persName><persName>Jean Knobloch</persName>1504), in-4°.  Schmidt III, n° 48.— Jadis bibl. de Strasbourg, Incun.  n° 3949.  3039  PSALTERIUM: cum apparatu vulgari firmiter appresso.—  <date>(</date>Strasbourg, <persName idref="119108860">Mathias Hupfuff</persName>1506), in-4°,  Vogeleis, p. 166. <date>(</date>B N Strasbourg R 101.082 <date>(</date>2) et R.102.156:  Ritter, Rép. n° 1942l.  3040  PSALTERIUM: cum apparatu vulgari... Lateinisch Psalter  mit dem teutschen dabey getruckt.— Strasbourg,  <date>Jean Prüss</date><persName idref="140812156">Jean Prüss</persName><persName>Jean Knobloch</persName><date>1508</date>, in-4°.  Schmidt VII, n° 41; Consistoire Colmar; Baer <date>(</date><placeName>Francfort s.</placeName> M.) Catal, 500 <date>(</date>1907), n° 1163; 60 M.; Vogeleis, p. 169;  Ritter: B M Strasbourg, n° 1765.  3041  430  </p>
    </div>
  </body>
</xml>
