<?xml version='1.0' encoding='UTF-8'?>
<xml>
  <body>
    <div>
      <p><persName>HUTTICH Joh</persName>,.: Libellus Imperatorum Romanorum, una  cum imaginibus...— Strasbourg, <persName>Wolfgang Köpfel</persName><date>1537</date>,  in-8°.( Ritter, Hist. impr. p. 248). [ Autres éd. de 1525, 1526, 1534 et <date>1552</date>; voir Ritter,  Rép, nos 1235- 1238).  2118  <persName>HUTTICH Joh</persName>,.( Idem).— Strasbourg, <persName>Wolfgang Köpfel</persName> <date>1540</date>, in-8°.( Ritter, Hist, impr. p. 248).  2119  HYGINUS:[ HIIgini Astronomi Von den bildern der zwölff  zaychen am himel mit ihren sternen und aygenschafften... — Strasbourg, <persName>Jacques Cammerlander</persName><date>1531</date>, in-40.  Zinner 1441.  2120  HYGINUS. Voir aussi: KALENDER n° 2189.  HYMNI: Hymni de tempore et de sanctis... denuo redacti...— ( Strasbourg, <persName>Jean Knobloch</persName><persName idref="140812156">Jean Prüss</persName>, <date>mars</date>1519), in-4°.  Panzer 6, 92, 558; Schmidt VII, n° 174: B N Munich.( Autres  éd. de <date>1513</date>et <date>1516</date>, voir Ritter, Rép. nos 1239-  1240l.  2121  HYMNI de tempore et de sanctis( éd. <persName>J. Wimpheling</persName>).—  <placeName>Haguenau</placeName>, <persName idref="034890890">Henri Gran</persName>1519, in-80.  Proctor 11.677( b).  2122  ICHER, Felix. Voir: AcTEN n° 741.  <persName>ILLKIRCH</persName>( <placeName>Bas-Rhin</placeName>),[ Jost vonl. Voir: HOFMANN, Melchior  n° 2035.  IMITATIO Christi( en allemand): Nachvolgung Christi und  verschmähung aller eitelkeil diser welt... Ist jetz aber¬  mal... von newem auszgangen.—( Strasbourg, <persName>Jean Knobloch</persName><persName idref="140812156">Jean Prüss</persName> , <date>28 mai 1544</date>), in-80.  Fromm: Die Ausgaben der Imitatio Christi in der Kölner  Stadtbibliothek.( Köln 1886), p. 20; Schmidt III, p. 42,  n° 52.( Édition <date>1552</date>voir Ritter, Rép. n° 2326l.  2123  260  </p>
    </div>
  </body>
</xml>
