<?xml version='1.0' encoding='UTF-8'?>
<xml>
  <body>
    <div>
      <p><persName>Paulus</persName>Runge genant <persName>. Berger</persName>Anno M.D.LVII <persName>. Berger</persName>— Strasbourg,  <persName>Jacques Frölich</persName><date>1557</date>, placard in- fol <persName>. Berger</persName><date>(</date>Vision de Runge,  l’ exhortant à prêcher aux hommes la pénitence) <date>(</date>Une  variante la même année, avec la seule souscription:  Getruckt zu Strassburg) <persName>. Berger</persName> Weller, Zeitungen, n° 221; Zurich, Bibl <persName>. Berger</persName>Centrale II, 4/1 <persName>. Berger</persName> 3587  ZEITUNG: Neue Zeitung von der Kirchen im eussern Moren¬  landt <persName>. Berger</persName>— Strasbourg, <persName>Th</persName><persName>. Berger</persName><date>1561 Augusti</date><persName>. Berger</persName> B M Colmar <persName>. Berger</persName> 3588  ZEITUNG: Ein dritt New Zeitung vom XXI, tag <date>Augusti</date> auss Wien, wie Jula wiederumb von den Türcken hefftig  belegert und beschossen ist worden <persName>. Berger</persName>Auch wie der  Türckisch Keyser drey seiner Obersten hat jamerlich  tödten lassen, darumb das sie von Jula und Vesperia  abzogen seind <persName>. Berger</persName>Und wie er mit den Christen, Mann,  Weib und Kind also unbermherzig umbgeht und hinweg  fürt <persName>. Berger</persName>— Strasbourg, <persName>Pierre Hug</persName><date>(</date><date>1566</date>), in-4° <date>(</date>2 éd <persName>. Berger</persName>de  Hans Zimmermann à <placeName>Augsbourg</placeName>avec la date du  <date>21 août 1566</date><date>1566</date>) <persName>. Berger</persName> Weller, Zeitungen, n° 305 <persName>. Berger</persName>Bibl <persName>. Berger</persName>Centrale Zurich <persName>. Berger</persName> 3589  ZEITUNG: Die vierdt New Zeittung, Welcher gestalt die  Römisch Key <persName>. Berger</persName>Maj mit... Ertzhertzog Ferdinanden zu  Osterreich... den zwölfften <date>Augusti</date>ausz Wien wieder  den Türckischen Feind ausgezogen und Was sich bis  auff den XXI <date>Augusti</date>zugetragen hat <persName>. Berger</persName>— Strasbourg,  <persName>Thiébaud Berger</persName><date>1566</date>, in-4° <persName>. Berger</persName> 3590  ZEITUNG: Die sibend new Zeittung aus der Kay <persName>. Berger</persName>Mayest <persName>. Berger</persName> Feldleger in Ungarn, jetz bei Gamorra den 4 <date>September</date> <date>1566</date><persName>. Berger</persName>— Strasbourg, <persName>Pierre Hug</persName><date>1566</date>, in-40 <persName>. Berger</persName> Weller, Zeitungen, n° 313 <persName>. Berger</persName>Bibl <persName>. Berger</persName>Centrale Zurich <persName>. Berger</persName> 3591  537  </p>
    </div>
  </body>
</xml>
