<?xml version='1.0' encoding='UTF-8'?>
<xml>
  <body>
    <div>
      <p><placeName>Strasbourg</placeName><date>vers 1573</date>), in-8°.  Voir: Hauffen:- Studien dans Euphorion III, p. 229,  Anm. 2.  1731 ( FISCHART, Joh.]( Wunderzeitung): Ain gewisse Wunder¬  zeitung von einer Schwangeren Jüdin zu Binzwangen...—  <placeName>Strasbourg</placeName>après <date>1574</date>. Graesse II, p. 586; Wickers¬  heimer, E.: Catalogue des Folia naturales res spectantia  a <persName>Johanne</persName>Hermann collecta. Dans Revue des Biblio¬  thèques n° 11/12( 1925), n° 100.  1732  FISCHART, Joh.: Beschläge zum Heiligthums kästlin. Heilig¬  thumsspang <persName>Jesuwalti Johann Fischart</persName>Pickhart—).  Voir: CALVIN, Jean. Brotkorb der H. Römischen  Reliquien.— <placeName>Strasbourg</placeName>1583.( Nouv. éd. 1584, 1590,  1594.) Voir n° 1270.  1733  FISCHART. Voir: ANTIMARTYRION n° 828; ARNAULD, Ant.  n° 856; BARNAUD n° 930/1; BESCHREIBUNG nOS 995, 997;  BULLINGER n° 1243; CALVIN n° 1270; CATECHISMUS  n° 1305a; ESTIENNE, H n° 1646; EUSTACHIUS n° 1666;  EULENSPIEGEL n° 1658; FRIEDENSARTICKEL n° 1772;  HAUFFEN dans Euphorion III- X; HERTZOG n° 2002;  HOLTZWART n° 2039; PATRIOT n° 2844/5; PROGNOSTICON  n° 2993; EGENOLF von Stauffenberg n° 1534;  WUNDERZEITUNGEN n° 3564; ZEITUNG nOS 3579, 3606. ( RITTER, Rép, nos 848- 865l.  FISCHFANG: Wie man Fisch und Vogel fahen soll mit den  henden...— <placeName>Strasbourg</placeName>, <date>s. d.</date>( <date>commencement XVIe</date>du  sièclel, in-40.  Copinger II, 2515; Voulliéme: <placeName>Berlin</placeName>2564.  1734  FISCHFANG: Wie man visch und vogel fahen soll...— ( <placeName>Strasbourg</placeName>, <persName idref="119108860">Mathias Hupfuff</persName>1508), in-4°.  Schmidt V, n° 72; Weller 470.  1735  185  </p>
    </div>
  </body>
</xml>
