<?xml version='1.0' encoding='UTF-8'?>
<xml>
  <body>
    <div>
      <p><date>.</date>A 2a: Ein vorred zu einnem ersammen weiszen Rat der  loblich,! en statt Bern <date>.</date> * R100.317 <date>.</date>Prov <date>.</date>: Bœr e Co <date>.</date>( Vente Karajan n° 58), Franc¬  fort- s.-M. 2/ V1 1875; 15 M. 50 <date>.</date>Ex-libris de Karajan <date>.</date> Au verso du f. de garde: Den 8 <date>.</date><date>April 1855</date>bei Schratt um I fl....  Diese Schrift Murners gehört zu den grössten Seltenheiten <date>.</date> Pème ex <date>.</date>:* R 100.318 <date>.</date>Prov <date>.</date>: Bibl <date>.</date>Ch <date>.</date>Schmidt avec son ex-libris,  les signatures fol <date>.</date>C et 12 sont différentes de celles de l’ ex <date>.</date>R100.317 <date>.</date> Liebenau: Murner <date>.</date>[— Erläuterungen zu <placeName>Janssens</placeName>Geschichte des  deutschen Volkes IX] <date>1913</date>p. 177 dit que le livre a été imprimé en <date>1521</date> à <placeName>Strasbourg</placeName>par Jean Pruss <date>.</date> 1613  Mistury Mun dru firr bruren Prtuiger  ordens der ob seruanz juà Mern mm Oßßweyger lano  verbzants in de jar nocb Ccbausti geburt <date>.</date>W.CC  CC.ix <date>.</date>vff oẽnehitẽ donderstag nob pfinastẽ.  1049  <date>1521</date> Rench vue¬ — Hocbsleat,  tin  Doct <date>.</date>Iesus — Due ac lestor  cnus luutb  et cet  pon Ber  PAIRON  LIBERIATIS <date>.</date> Conciliabulii malignantium <date>.</date> CEin hurtzer brgriff unhillicber frrurt  handlung Nochitrate, Murnars, Doctoz Ipesue¬  vn irer anbend er/mider den Christlicben  Poctoz Martin Autbers pon alle  lacbhaber kuangclisther lere, ( Voir p. 1048, n° 1613)  </p>
    </div>
  </body>
</xml>
